objectscope/__init__.py
objectscope/anchor_bbox_utils.py
objectscope/evaluator.py
objectscope/model_export_utils.py
objectscope/torch_tf.Dockerfile
objectscope/train_pipeline.py
objectscope/trainer.py
objectscope/utils.py
objectscope-1.16.9.dist-info/LICENSE
objectscope-1.16.9.dist-info/METADATA
objectscope-1.16.9.dist-info/WHEEL
objectscope-1.16.9.dist-info/entry_points.txt
objectscope-1.16.9.dist-info/RECORD
