Metadata-Version: 2.3
Name: objectscope
Version: 1.16.9
Summary: Object detection
License: MIT
Author: Agbleze
Requires-Python: >=3.10.14,<4.0.0
Classifier: License :: OSI Approved :: MIT License
Classifier: Programming Language :: Python :: 3
Classifier: Programming Language :: Python :: 3.11
Classifier: Programming Language :: Python :: 3.12
Classifier: Programming Language :: Python :: 3.13
Requires-Dist: cpauger (==1.1.2)
Requires-Dist: matplotlib (==3.9.2)
Requires-Dist: matplotlib-inline (==0.1.7)
Requires-Dist: matplotlib-venn (==0.11.10)
Requires-Dist: numpy (==1.26.4)
Requires-Dist: onnx (==1.16.1)
Requires-Dist: onnx-ir (==0.1.4)
Requires-Dist: onnxconverter-common (==1.14.0)
Requires-Dist: onnxoptimizer (==0.3.13)
Requires-Dist: onnxruntime (==1.22.1)
Requires-Dist: onnxruntime-genai (==0.9.0)
Requires-Dist: onnxruntime-genai-cuda (==0.9.0)
Requires-Dist: onnxruntime-gpu (==1.22.0)
Requires-Dist: onnxscript (==0.3.2)
Requires-Dist: opencv-contrib-python (==4.10.0.84)
Requires-Dist: opencv-python (==4.10.0.84)
Requires-Dist: opencv-python-headless (==4.10.0.84)
Requires-Dist: pandas (==2.2.3)
Requires-Dist: plotly (==5.18.0)
Requires-Dist: python-decouple (==3.8)
Requires-Dist: tensorboard (==2.15.2)
Requires-Dist: tops (==0.2.0)
Requires-Dist: torch (==2.1.1+cu118)
Requires-Dist: torchvision (==0.16.1+cu118)
Requires-Dist: typing (==3.7.4.3)
